quantile_scatter/__init__.py
quantile_scatter/test.py
quantile_scatter-0.3.4.dist-info/METADATA
quantile_scatter-0.3.4.dist-info/WHEEL
quantile_scatter-0.3.4.dist-info/top_level.txt
quantile_scatter-0.3.4.dist-info/RECORD
